napari_hydra/__init__.py
napari_hydra/plugin.py
napari_hydra/hydrastardist/__init__.py
napari_hydra/hydrastardist/blocks_hydra.py
napari_hydra/hydrastardist/data/__init__.py
napari_hydra/hydrastardist/data/image_datasets.py
napari_hydra/hydrastardist/data/image_mask_datasets.py
napari_hydra/hydrastardist/models/__init__.py
napari_hydra/hydrastardist/models/base_hydra.py
napari_hydra/hydrastardist/models/metrics.py
napari_hydra/hydrastardist/models/model2d_hydra.py
napari_hydra/hydrastardist/utils/__init__.py
napari_hydra/hydrastardist/utils/config.py
napari_hydra/hydrastardist/utils/data.py
napari_hydra/hydrastardist/utils/hydranet.py
napari_hydra/hydrastardist/utils/plot_utils.py
napari_hydra/hydrastardist/utils/six.py
napari_hydra/hydrastardist/utils/tf.py
napari_hydra/hydrastardist/utils/utils.py
napari_hydra/utils/__init__.py
napari_hydra/utils/ensure_default_model.py
napari_hydra/utils/export.py
napari_hydra/utils/fine_tune.py
napari_hydra/utils/is_image_stack.py
napari_hydra/utils/layer.py
napari_hydra/utils/make_divisible.py
napari_hydra/utils/process_frame.py
napari_hydra/utils/rasterize_labels.py
napari_hydra/utils/well_processing.py
napari_hydra-0.0.2.dist-info/METADATA
napari_hydra-0.0.2.dist-info/WHEEL
napari_hydra-0.0.2.dist-info/entry_points.txt
napari_hydra-0.0.2.dist-info/top_level.txt
napari_hydra-0.0.2.dist-info/RECORD
