Metadata-Version: 2.4
Name: napari-hydra
Version: 0.0.2
Summary: Napari Hydra Plugin - GUI-based nested object detection
Author-email: Henrique Romão <henriquepromao@outlook.com>, Trina De <t.de@hzdr.de>, Artur Yakimovich <a.yakimovich@hzdr.de>
License-Expression: BSD-3-Clause
Project-URL: Homepage, https://github.com/casus/HydraStarDist
Project-URL: Issues, https://github.com/casus/HydraStarDist/issues
Classifier: Framework :: napari
Classifier: Development Status :: 4 - Beta
Classifier: Intended Audience :: Science/Research
Classifier: Topic :: Scientific/Engineering
Classifier: Operating System :: OS Independent
Classifier: Programming Language :: Python :: 3.9
Classifier: Programming Language :: Python :: 3.10
Classifier: Programming Language :: Python :: 3.11
Requires-Python: >=3.9
Requires-Dist: napari[all]
Requires-Dist: csbdeep>=0.7.4
Requires-Dist: scikit-image
Requires-Dist: numba
Requires-Dist: imageio
Requires-Dist: stardist>=0.9.1
Requires-Dist: tensorflow>=2.6
Requires-Dist: typing_extensions>=4.12
Provides-Extra: tf1
Requires-Dist: csbdeep[tf1]>=0.7.4; extra == "tf1"
Provides-Extra: test
Requires-Dist: pytest>=7.2.0; extra == "test"
Provides-Extra: bioimageio
Requires-Dist: bioimageio.core>=0.5.0; extra == "bioimageio"
Requires-Dist: importlib-metadata; extra == "bioimageio"
